audiotag/__init__.py
audiotag/audiotag.py
audiotag/modes.py
audiotag/py.typed
audiotag/styles.py
audiotag/track.py
audiotag/util.py
audiotag/config/__init__.py
audiotag-0.7.3.data/scripts/audiotag
audiotag-0.7.3.dist-info/LICENSE
audiotag-0.7.3.dist-info/METADATA
audiotag-0.7.3.dist-info/WHEEL
audiotag-0.7.3.dist-info/top_level.txt
audiotag-0.7.3.dist-info/RECORD
