Metadata-Version: 2.1
Name: audiotag
Version: 0.7.3
Summary: A simple CLI audio tagger
Author: Simon Rose
Author-email: mail@popkornium18.de
License: MIT
Platform: linux
Classifier: Programming Language :: Python :: 3
Classifier: Programming Language :: Python :: 3 :: Only
Classifier: Programming Language :: Python :: 3.8
Classifier: Programming Language :: Python :: 3.9
Classifier: Programming Language :: Python :: 3.10
Classifier: License :: OSI Approved :: MIT License
Classifier: Operating System :: POSIX :: Linux
Classifier: Operating System :: MacOS
Classifier: Operating System :: Microsoft :: Windows
Classifier: Intended Audience :: End Users/Desktop
Requires-Python: >=3.8
License-File: LICENSE
Requires-Dist: pytaglib
Requires-Dist: appdirs
Requires-Dist: prompt-toolkit
Provides-Extra: testing
Requires-Dist: Cython (>=0.29.0) ; extra == 'testing'
Requires-Dist: pytest (>=6.0) ; extra == 'testing'
Requires-Dist: pytest-cov (>=3.0) ; extra == 'testing'
Requires-Dist: mypy (>=0.910) ; extra == 'testing'
Requires-Dist: flake8 (>=4.0) ; extra == 'testing'
Requires-Dist: tox (>=3.24) ; extra == 'testing'
